{
  "extends": "../tslint.json",
  "rules": {
    "directive-selector": [
      true,
      "attribute",
      "app",
      "camelCase"
    ],
    "component-selector": [
      true,
      "element",
      "app",
      "kebab-case"
    ],
    "variable-name": [
      true,
      "allow-leading-underscore"
    ],
    "member-access": [
      true,
      "check-accessor",
      "check-parameter-property",
      "check-constructor"
    ],
    "member-ordering": [
      true,
      {
        "order": "fields-first"
      }
    ],
    "no-misused-new": true,
    "no-return-await": true,
    "prefer-readonly": true,
    "ordered-imports": true
  }
}